LICENSE.txt
README.md
setup.cfg
setup.py
jupylet/__init__.py
jupylet/app.py
jupylet/clock.py
jupylet/collision.py
jupylet/color.py
jupylet/env.py
jupylet/event.py
jupylet/label.py
jupylet/loader.py
jupylet/lru.py
jupylet/model.py
jupylet/node.py
jupylet/resource.py
jupylet/rl.py
jupylet/shadertoy.py
jupylet/sprite.py
jupylet/state.py
jupylet/utils.py
jupylet.egg-info/PKG-INFO
jupylet.egg-info/SOURCES.txt
jupylet.egg-info/dependency_links.txt
jupylet.egg-info/requires.txt
jupylet.egg-info/top_level.txt
jupylet/assets/fonts/SIL Open Font License.txt
jupylet/assets/fonts/SourceSerifPro-Bold.otf
jupylet/assets/shaders/default-fragment-shader.glsl
jupylet/assets/shaders/default-vertex-shader.glsl
jupylet/assets/shaders/shadertoy-wrapper.glsl
jupylet/assets/shaders/sprite.glsl
jupylet/assets/sounds/impulses/InsidePiano.flac
jupylet/assets/sounds/impulses/MaesHowe.flac
jupylet/assets/sounds/impulses/README.md
jupylet/assets/sounds/impulses/StAndrewsChurch.flac
jupylet/audio/__init__.py
jupylet/audio/bundle.py
jupylet/audio/device.py
jupylet/audio/effects.py
jupylet/audio/filters.py
jupylet/audio/midi.py
jupylet/audio/note.py
jupylet/audio/sample.py
jupylet/audio/sound.py
jupylet/audio/synth.py