Metadata-Version: 2.1
Name: jupylet
Version: 0.9.2
Summary: Python game programming in Jupyter notebooks.
Home-page: https://github.com/nir/jupylet
Download-URL: https://github.com/nir/jupylet/archive/v0.9.2.tar.gz
Author: Nir Aides
Author-email: nir.8bit@gmail.com
License: bsd-2-clause
Keywords: reinforcement learning,deep learning,synthesizers,moderngl,children,jupyter,python,games,midi,kids,RL
Classifier: Development Status :: 4 - Beta
Classifier: Intended Audience :: Education
Classifier: Intended Audience :: Developers
Classifier: Intended Audience :: Science/Research
Classifier: Topic :: Education
Classifier: Topic :: Multimedia :: Graphics
Classifier: Topic :: Multimedia :: Graphics :: 3D Rendering
Classifier: Topic :: Multimedia :: Sound/Audio
Classifier: Topic :: Multimedia :: Sound/Audio :: MIDI
Classifier: Topic :: Multimedia :: Sound/Audio :: Sound Synthesis
Classifier: Topic :: Scientific/Engineering :: Artificial Intelligence
Classifier: License :: OSI Approved :: BSD License
Classifier: Programming Language :: Python :: 3.9
Classifier: Programming Language :: Python :: 3.10
Classifier: Programming Language :: Python :: 3.11
Classifier: Programming Language :: Python :: 3.12
Requires-Python: >=3.9,<3.13
License-File: LICENSE.txt
Requires-Dist: glfw
Requires-Dist: mido
Requires-Dist: tqdm
Requires-Dist: jedi
Requires-Dist: numpy
Requires-Dist: PyGLM
Requires-Dist: scipy
Requires-Dist: pillow
Requires-Dist: gltflib
Requires-Dist: jupyter
Requires-Dist: notebook
Requires-Dist: moderngl
Requires-Dist: soundfile
Requires-Dist: webcolors
Requires-Dist: ipyevents
Requires-Dist: ipywidgets
Requires-Dist: matplotlib
Requires-Dist: sounddevice
Requires-Dist: soundcard; platform_system == "Darwin"
Requires-Dist: python-rtmidi
Requires-Dist: moderngl-window
Provides-Extra: midi
Requires-Dist: python-rtmidi; extra == "midi"
